fmu/__init__.py
fmu/__main__.py
fmu/cli.py
fmu/core.py
fmu/search.py
fmu/specs.py
fmu/update.py
fmu/validation.py
frontmatter_utils-0.24.0.dist-info/licenses/LICENSE
tests/__init__.py
tests/test_cli.py
tests/test_core.py
tests/test_search.py
tests/test_specs.py
tests/test_update.py
tests/test_validation.py
frontmatter_utils-0.24.0.dist-info/METADATA
frontmatter_utils-0.24.0.dist-info/WHEEL
frontmatter_utils-0.24.0.dist-info/entry_points.txt
frontmatter_utils-0.24.0.dist-info/top_level.txt
frontmatter_utils-0.24.0.dist-info/RECORD
